dp832/__init__.py
dp832/dp832.py
pydp832_tspspi-0.0.4.dist-info/LICENSE.md
pydp832_tspspi-0.0.4.dist-info/METADATA
pydp832_tspspi-0.0.4.dist-info/WHEEL
pydp832_tspspi-0.0.4.dist-info/top_level.txt
pydp832_tspspi-0.0.4.dist-info/RECORD
